Metadata-Version: 2.1
Name: offsets
Version: 1.38.75
Summary: do you want to get all csgo offsets? Ok, use class csgo, enjoy :)
Home-page: UNKNOWN
Author-email: adamisaev92341@gmail.com
License: UNKNOWN
Platform: UNKNOWN
